LICENSE
MANIFEST.in
README
setup.py
django_voter.egg-info/PKG-INFO
django_voter.egg-info/SOURCES.txt
django_voter.egg-info/dependency_links.txt
django_voter.egg-info/requires.txt
django_voter.egg-info/top_level.txt
ratings/__init__.py
ratings/__init__.pyc
ratings/admin.py
ratings/compute.py
ratings/middleware.py
ratings/models.py
ratings/tasks.py
ratings/urls.py
ratings/views.py
ratings/management/__init__.py
ratings/management/commands/__init__.py
ratings/management/commands/recount_ratings.py
ratings/migrations/0001_initial.py
ratings/migrations/0002_auto__chg_field_score_score.py
ratings/migrations/0003_add_model_Rating_add_model_RatingVote.py
ratings/migrations/0004_move_ratings_old_to_new.py
ratings/migrations/0005_auto__del_vote__del_unique_vote_content_type_object_id_user__del_score.py
ratings/migrations/0006_auto__add_field_badge_rating_bonus.py
ratings/migrations/__init__.py
ratings/templatetags/__init__.py
ratings/templatetags/ratings_tags.py