Metadata-Version: 1.0
Name: django-voter
Version: 0.1.0
Summary: Application for Django framework that contains generic rating\vote system. Requires modifications in the model, that will be used for voting, to optimize number of database queries.
Home-page: http://github.com/ilblackdragon/django-voter.git
Author: Illia Polosukhin
Author-email: ilblackdragon@gmail.com
License: MIT
Platform: UNKNOWN
